VNDUtils/Generators.py
VNDUtils/Metrics.py
VNDUtils/__init__.py
VNDUtils-0.0.1.dist-info/LICENSE.txt
VNDUtils-0.0.1.dist-info/METADATA
VNDUtils-0.0.1.dist-info/WHEEL
VNDUtils-0.0.1.dist-info/top_level.txt
VNDUtils-0.0.1.dist-info/RECORD
